kwenta/__init__.py
kwenta/constants.py
kwenta/kwenta.py
kwenta/alerts/__init__.py
kwenta/alerts/alerts.py
kwenta/cli/__init__.py
kwenta/cli/kwenta_cli.py
kwenta/contracts/__init__.py
kwenta/contracts/contracts.py
kwenta/contracts/json/PerpsV2ExchangeRate.json
kwenta/contracts/json/PerpsV2Market.json
kwenta/contracts/json/PerpsV2MarketData.json
kwenta/contracts/json/PerpsV2MarketSettings.json
kwenta/contracts/json/PerpsV2MarketState.json
kwenta/contracts/json/PerpsV2MarketViews.json
kwenta/contracts/json/SMAccount.json
kwenta/contracts/json/SMFactory.json
kwenta/contracts/json/__init__.py
kwenta/contracts/json/sUSD.json
kwenta/pyth/__init__.py
kwenta/pyth/constants.py
kwenta/pyth/pyth.py
kwenta/queries/__init__.py
kwenta/queries/config.py
kwenta/queries/gql.py
kwenta/queries/queries.py
kwenta-1.2.0.dist-info/METADATA
kwenta-1.2.0.dist-info/WHEEL
kwenta-1.2.0.dist-info/entry_points.txt
kwenta-1.2.0.dist-info/top_level.txt
kwenta-1.2.0.dist-info/RECORD
