Metadata-Version: 2.1
Name: kwenta
Version: 1.2.0
Summary: Python SDK for Kwenta
Author: Kwenta DAO
Classifier: Intended Audience :: Developers
Classifier: License :: OSI Approved :: MIT License
Classifier: Programming Language :: Python :: 3
Classifier: Programming Language :: Python :: 3.6
Classifier: Programming Language :: Python :: 3.7
Classifier: Programming Language :: Python :: 3.8
Classifier: Programming Language :: Python :: 3.9
Classifier: Programming Language :: Python :: 3.10
Requires-Python: >=3.8
Requires-Dist: numpy
Requires-Dist: pandas
Requires-Dist: requests
Requires-Dist: web3 >=6.0.0
Requires-Dist: gql
